{
    "subjectId":  "geography",
    "gradeId":  "cp",
    "title":  "géographie CP",
    "categories":  {
                       "cp-se-reperer":  [
                                             {
                                                 "question":  "Pour aller en haut d'un escalier, on monte ou on descend ?",
                                                 "choices":  [
                                                                 "On monte",
                                                                 "On descend",
                                                                 "On dort"
                                                             ],
                                                 "answer":  "On monte"
                                             },
                                             {
                                                 "question":  "La cour de recreation se trouve...",
                                                 "choices":  [
                                                                 "dans l'école",
                                                                 "dans la mer",
                                                                 "dans la lune"
                                                             ],
                                                 "answer":  "dans l'école"
                                             },
                                             {
                                                 "question":  "Pour retrouver un lieu sur un dessin, on peut utiliser...",
                                                 "choices":  [
                                                                 "un plan",
                                                                 "une casserole",
                                                                 "un ballon"
                                                             ],
                                                 "answer":  "un plan"
                                             },
                                             {
                                                 "question":  "La classe est souvent à l'interieur ou à l'exterieur ?",
                                                 "choices":  [
                                                                 "A l'interieur",
                                                                 "A l'exterieur",
                                                                 "Dans le ciel"
                                                             ],
                                                 "answer":  "A l'interieur"
                                             },
                                             {
                                                 "question":  "Devant toi, c'est...",
                                                 "choices":  [
                                                                 "en face",
                                                                 "derriere",
                                                                 "sous terre"
                                                             ],
                                                 "answer":  "en face"
                                             },
                                             {
                                                 "question":  "Pour retrouver la bibliothèque de l'école, un plan peut aider à...",
                                                 "choices":  [
                                                                 "se repérer",
                                                                 "chanter",
                                                                 "mesurer le temps"
                                                             ],
                                                 "answer":  "se repérer"
                                             },
                                             {
                                                 "question":  "Pour retrouver la bibliothèque de l'école, un plan peut aider à...",
                                                 "choices":  [
                                                                 "se repérer",
                                                                 "chanter",
                                                                 "mesurer le temps"
                                                             ],
                                                 "answer":  "se repérer"
                                             }
                                         ],
                       "cp-paysages":  [
                                           {
                                               "question":  "A la montagne, on voit souvent...",
                                               "choices":  [
                                                               "des sommets",
                                                               "des vagues",
                                                               "des gratte-ciel"
                                                           ],
                                               "answer":  "des sommets"
                                           },
                                           {
                                               "question":  "A la mer, on trouve...",
                                               "choices":  [
                                                               "une plage",
                                                               "un glacier",
                                                               "un volcan"
                                                           ],
                                               "answer":  "une plage"
                                           },
                                           {
                                               "question":  "En ville, il y a souvent...",
                                               "choices":  [
                                                               "beaucoup de rues",
                                                               "des champs partout",
                                                               "des igloos"
                                                           ],
                                               "answer":  "beaucoup de rues"
                                           },
                                           {
                                               "question":  "A la campagne, on peut voir...",
                                               "choices":  [
                                                               "des champs",
                                                               "des metros partout",
                                                               "des fusees"
                                                           ],
                                               "answer":  "des champs"
                                           },
                                           {
                                               "question":  "Une rivière est...",
                                               "choices":  [
                                                               "de l'eau qui coule",
                                                               "une route",
                                                               "une maison"
                                                           ],
                                               "answer":  "de l'eau qui coule"
                                           },
                                           {
                                               "question":  "Un lac contient surtout...",
                                               "choices":  [
                                                               "de l'eau",
                                                               "du bitume",
                                                               "des escaliers"
                                                           ],
                                               "answer":  "de l'eau"
                                           },
                                           {
                                               "question":  "Un lac contient surtout...",
                                               "choices":  [
                                                               "de l'eau",
                                                               "du bitume",
                                                               "des escaliers"
                                                           ],
                                               "answer":  "de l'eau"
                                           }
                                       ],
                       "cp-transports-lieux":  [
                                                   {
                                                       "question":  "Le bus sert à...",
                                                       "choices":  [
                                                                       "se deplacer",
                                                                       "arroser les plantes",
                                                                       "cuisiner"
                                                                   ],
                                                       "answer":  "se deplacer"
                                                   },
                                                   {
                                                       "question":  "Le train roule surtout...",
                                                       "choices":  [
                                                                       "sur des rails",
                                                                       "dans la mer",
                                                                       "dans le ciel"
                                                                   ],
                                                       "answer":  "sur des rails"
                                                   },
                                                   {
                                                       "question":  "Le trottoir est fait pour...",
                                                       "choices":  [
                                                                       "marcher",
                                                                       "nager",
                                                                       "dormir"
                                                                   ],
                                                       "answer":  "marcher"
                                                   },
                                                   {
                                                       "question":  "Un pont permet souvent de passer...",
                                                       "choices":  [
                                                                       "au-dessus de l'eau",
                                                                       "sous la classe",
                                                                       "dans les nuages"
                                                                   ],
                                                       "answer":  "au-dessus de l'eau"
                                                   },
                                                   {
                                                       "question":  "La gare est un lieu ou l'on prend souvent...",
                                                       "choices":  [
                                                                       "le train",
                                                                       "un bateau de peche",
                                                                       "un ascenseur"
                                                                   ],
                                                       "answer":  "le train"
                                                   },
                                                   {
                                                       "question":  "Pour traverser la rue, on utilise...",
                                                       "choices":  [
                                                                       "un passage pieton",
                                                                       "une barque",
                                                                       "une echelle"
                                                                   ],
                                                       "answer":  "un passage pieton"
                                                   }
                                               ]
                   }
}