{
    "title":  "Géométrie CE1",
    "gradeId":  "ce1",
    "subjectId":  "math",
    "categories":  {
                       "ce1-formes-solides-planes":  [
                                                        {
                                                            "question":  "Lequel est une forme plane ?",
                                                            "choices":  [
                                                                            "Le triangle",
                                                                            "La boule",
                                                                            "Le cube"
                                                                        ],
                                                            "answer":  "Le triangle"
                                                        },
                                                        {
                                                            "question":  "Le rectangle est une figure...",
                                                            "choices":  [
                                                                            "plane",
                                                                            "en volume",
                                                                            "sans côté"
                                                                        ],
                                                            "answer":  "plane"
                                                        },
                                                        {
                                                            "question":  "Un cube est...",
                                                            "choices":  [
                                                                            "un solide",
                                                                            "un triangle",
                                                                            "un cercle"
                                                                        ],
                                                            "answer":  "un solide"
                                                        },
                                                        {
                                                            "question":  "Le cercle est...",
                                                            "choices":  [
                                                                            "une forme plane",
                                                                            "un solide",
                                                                            "un angle"
                                                                        ],
                                                            "answer":  "une forme plane"
                                                        },
                                                        {
                                                            "question":  "Lequel est un solide ?",
                                                            "choices":  [
                                                                            "Le pavé droit",
                                                                            "Le carré",
                                                                            "Le segment"
                                                                        ],
                                                            "answer":  "Le pavé droit"
                                                        },
                                                        {
                                                            "question":  "Une boîte à chaussures ressemble à...",
                                                            "choices":  [
                                                                            "un pavé droit",
                                                                            "un cercle",
                                                                            "un triangle"
                                                                        ],
                                                            "answer":  "un pavé droit"
                                                        },
                                                        {
                                                            "question":  "Le carré a...",
                                                            "choices":  [
                                                                            "4 côtés égaux",
                                                                            "3 côtés",
                                                                            "aucun côté"
                                                                        ],
                                                            "answer":  "4 côtés égaux"
                                                        },
                                                        {
                                                            "question":  "Le triangle a...",
                                                            "choices":  [
                                                                            "3 côtés",
                                                                            "4 côtés",
                                                                            "5 côtés"
                                                                        ],
                                                            "answer":  "3 côtés"
                                                        }
                                                    ],
                       "ce1-longueurs-mesures":  [
                                                    {
                                                        "question":  "L'unité souvent utilisée pour mesurer un crayon est...",
                                                        "choices":  [
                                                                        "le centimètre",
                                                                        "le litre",
                                                                        "le kilogramme"
                                                                    ],
                                                        "answer":  "le centimètre"
                                                    },
                                                    {
                                                        "question":  "100 centimètres font...",
                                                        "choices":  [
                                                                        "1 mètre",
                                                                        "10 mètres",
                                                                        "1 litre"
                                                                    ],
                                                        "answer":  "1 mètre"
                                                    },
                                                    {
                                                        "question":  "Pour mesurer la longueur de la classe, on choisit plutôt...",
                                                        "choices":  [
                                                                        "le mètre",
                                                                        "le centimètre seul",
                                                                        "la minute"
                                                                    ],
                                                        "answer":  "le mètre"
                                                    },
                                                    {
                                                        "question":  "Une ficelle de 80 cm est ... qu'une ficelle de 1 m.",
                                                        "choices":  [
                                                                        "plus courte",
                                                                        "plus longue",
                                                                        "de même longueur"
                                                                    ],
                                                        "answer":  "plus courte"
                                                    },
                                                    {
                                                        "question":  "Si deux segments mesurent 12 cm, ils sont...",
                                                        "choices":  [
                                                                        "de même longueur",
                                                                        "forcément perpendiculaires",
                                                                        "de couleurs différentes"
                                                                    ],
                                                        "answer":  "de même longueur"
                                                    },
                                                    {
                                                        "question":  "Quel outil sert à mesurer ?",
                                                        "choices":  [
                                                                        "La règle graduée",
                                                                        "Le compas de tableau",
                                                                        "Le pinceau"
                                                                    ],
                                                        "answer":  "La règle graduée"
                                                    },
                                                    {
                                                        "question":  "Lequel est le plus long ?",
                                                        "choices":  [
                                                                        "25 cm",
                                                                        "15 cm",
                                                                        "9 cm"
                                                                    ],
                                                        "answer":  "25 cm"
                                                    },
                                                    {
                                                        "question":  "Pour comparer deux longueurs, il faut...",
                                                        "choices":  [
                                                                        "utiliser la même unité",
                                                                        "changer d'unité à chaque fois",
                                                                        "ignorer les nombres"
                                                                    ],
                                                        "answer":  "utiliser la même unité"
                                                    }
                                                ],
                       "ce1-reperes-journee":  [
                                                  {
                                                      "question":  "Quel moment vient après le matin ?",
                                                      "choices":  [
                                                                      "Le midi",
                                                                      "La nuit",
                                                                      "Le soir"
                                                                  ],
                                                      "answer":  "Le midi"
                                                  },
                                                  {
                                                      "question":  "L'après-midi vient...",
                                                      "choices":  [
                                                                      "après midi",
                                                                      "avant le matin",
                                                                      "avant l'aube"
                                                                  ],
                                                      "answer":  "après midi"
                                                  },
                                                  {
                                                      "question":  "Le dîner se prend souvent...",
                                                      "choices":  [
                                                                      "le soir",
                                                                      "le matin",
                                                                      "à l'école"
                                                                  ],
                                                      "answer":  "le soir"
                                                  },
                                                  {
                                                      "question":  "Ordre correct d'une journée:",
                                                      "choices":  [
                                                                      "matin, midi, après-midi, soir",
                                                                      "soir, midi, matin, après-midi",
                                                                      "midi, matin, soir, après-midi"
                                                                  ],
                                                      "answer":  "matin, midi, après-midi, soir"
                                                  },
                                                  {
                                                      "question":  "Le petit-déjeuner est pris plutôt...",
                                                      "choices":  [
                                                                      "le matin",
                                                                      "la nuit",
                                                                      "le soir tard"
                                                                  ],
                                                      "answer":  "le matin"
                                                  },
                                                  {
                                                      "question":  "Après le soir, vient souvent...",
                                                      "choices":  [
                                                                      "la nuit",
                                                                      "le midi",
                                                                      "l'après-midi"
                                                                  ],
                                                      "answer":  "la nuit"
                                                  },
                                                  {
                                                      "question":  "À quel moment va-t-on souvent à l'école ?",
                                                      "choices":  [
                                                                      "Le matin",
                                                                      "Au milieu de la nuit",
                                                                      "Uniquement le soir"
                                                                  ],
                                                      "answer":  "Le matin"
                                                  },
                                                  {
                                                      "question":  "Le coucher du soleil annonce souvent...",
                                                      "choices":  [
                                                                      "le soir",
                                                                      "le matin",
                                                                      "midi"
                                                                  ],
                                                      "answer":  "le soir"
                                                  }
                                              ]
                   }
}
